code2graph/__init__.py
code2graph/code2graph.py
code2graph-0.0.5.data/scripts/code2graph.py
code2graph-0.0.5.dist-info/LICENSE
code2graph-0.0.5.dist-info/METADATA
code2graph-0.0.5.dist-info/WHEEL
code2graph-0.0.5.dist-info/top_level.txt
code2graph-0.0.5.dist-info/RECORD
