Metadata-Version: 2.1
Name: code2graph
Version: 0.0.5
Summary: A package for creating directed graph from python files
Home-page: https://gitlab.com/avarf/code2graph
Author: Ali Varfan
License: UNKNOWN
Platform: UNKNOWN
Classifier: Programming Language :: Python :: 3
Classifier: License :: OSI Approved :: MIT License
Classifier: Operating System :: OS Independent
Requires-Python: >=3.6
Requires-Dist: pygraphviz
